odoo/addons/ssi_mail_optional_related_attachment/README.rst
odoo/addons/ssi_mail_optional_related_attachment/__init__.py
odoo/addons/ssi_mail_optional_related_attachment/__manifest__.py
odoo/addons/ssi_mail_optional_related_attachment/models/__init__.py
odoo/addons/ssi_mail_optional_related_attachment/models/mail_template.py
odoo/addons/ssi_mail_optional_related_attachment/models/mail_template_related_attachment_category.py
odoo/addons/ssi_mail_optional_related_attachment/security/ir.model.access.csv
odoo/addons/ssi_mail_optional_related_attachment/static/description/icon.png
odoo/addons/ssi_mail_optional_related_attachment/views/mail_template_views.xml
odoo14_addon_ssi_mail_optional_related_attachment-14.0.1.0.2.dev1.dist-info/METADATA
odoo14_addon_ssi_mail_optional_related_attachment-14.0.1.0.2.dev1.dist-info/WHEEL
odoo14_addon_ssi_mail_optional_related_attachment-14.0.1.0.2.dev1.dist-info/top_level.txt
odoo14_addon_ssi_mail_optional_related_attachment-14.0.1.0.2.dev1.dist-info/RECORD
